{
    "example_source": [
        "x我还",
        "澄清",
        "了",
        "在该",
        "会议上",
        "提出的",
        "若干",
        "事项",
        "。"
    ],
    "example_target": [
        "<s>",
        "xi",
        "xwas",
        "xable",
        "xto",
        "xprovide",
        "xclarification",
        "xon",
        "xsome",
        "xof",
        "xthe",
        "xmatters",
        "xwhich",
        "xwere",
        "xraised",
        "xat",
        "xthat",
        "xmeeting",
        ".",
        "</s>"
    ],
    "hypotheses": [
        {
            "hypothesis": [
                "xi",
                "xam",
                "xalso",
                "xpleased",
                "xto",
                "xclarify",
                "xa",
                "xnumber",
                "xof",
                "xmatters",
                "xrelating",
                "xto",
                "xthe",
                "xmeeting",
                "."
            ],
            "score": -15.43970012664795
        },
        {
            "hypothesis": [
                "xi",
                "xam",
                "xalso",
                "xpleased",
                "xto",
                "xnote",
                "xthat",
                "xa",
                "xnumber",
                "xof",
                "xmatters",
                "xrelating",
                "xto",
                "xthe",
                "xmeeting",
                "."
            ],
            "score": -15.532397270202637
        },
        {
            "hypothesis": [
                "xi",
                "xam",
                "xalso",
                "xpleased",
                "xto",
                "xnote",
                "xthat",
                "xa",
                "xnumber",
                "xof",
                "xmatters",
                "xrelating",
                "xto",
                "xthe",
                "xconference",
                "."
            ],
            "score": -16.064302444458008
        },
        {
            "hypothesis": [
                "xi",
                "xam",
                "xalso",
                "xpleased",
                "xto",
                "xclarify",
                "xa",
                "xnumber",
                "xof",
                "xa",
                "xnumber",
                "xof",
                "xmatters",
                "xin",
                "xthis",
                "xmeeting",
                "."
            ],
            "score": -16.91337013244629
        },
        {
            "hypothesis": [
                "xi",
                "xam",
                "xalso",
                "xpleased",
                "xto",
                "xclarify",
                "xa",
                "xnumber",
                "xof",
                "xa",
                "xnumber",
                "xof",
                "xmatters",
                "xrelating",
                "xto",
                "xthe",
                "xmeeting",
                "."
            ],
            "score": -17.390094757080078
        },
        {
            "hypothesis": [
                "xi",
                "xam",
                "xalso",
                "xpleased",
                "xto",
                "xclarify",
                "xa",
                "xnumber",
                "xof",
                "xa",
                "xnumber",
                "xof",
                "xmatters",
                "xrelating",
                "xto",
                "xthe",
                "xconference",
                "."
            ],
            "score": -17.956926345825195
        },
        {
            "hypothesis": [
                "xi",
                "xam",
                "xalso",
                "xpleased",
                "xto",
                "xclarify",
                "xa",
                "xnumber",
                "xof",
                "xa",
                "xnumber",
                "xof",
                "xmatters",
                "xrelating",
                "xto",
                "xthis",
                "xmeeting",
                "."
            ],
            "score": -18.144372940063477
        },
        {
            "hypothesis": [
                "xi",
                "xam",
                "xalso",
                "xpleased",
                "xto",
                "xclarify",
                "xa",
                "xnumber",
                "xof",
                "xa",
                "xnumber",
                "xof",
                "xa",
                "xnumber",
                "xof",
                "xmatters",
                "xin",
                "xthis",
                "xmeeting",
                "."
            ],
            "score": -20.176712036132812
        },
        {
            "hypothesis": [
                "xi",
                "xam",
                "xalso",
                "xpleased",
                "xto",
                "xclarify",
                "xa",
                "xnumber",
                "xof",
                "xa",
                "xnumber",
                "xof",
                "xa",
                "xnumber",
                "xof",
                "xmatters",
                "xrelating",
                "xto",
                "xthe",
                "xmeeting",
                "."
            ],
            "score": -20.617340087890625
        },
        {
            "hypothesis": [
                "xi",
                "xam",
                "xalso",
                "xpleased",
                "xto",
                "xclarify",
                "xa",
                "xnumber",
                "xof",
                "xa",
                "xnumber",
                "xof",
                "xa",
                "xnumber",
                "xof",
                "xmatters",
                "xrelating",
                "xto",
                "xthe",
                "xconference",
                "."
            ],
            "score": -21.114276885986328
        }
    ],
    "diagnostic_info": "eyJ0IjogIjIwMjQtMDctMThUMDY6NDQ6MTAuMzcyNTUwIiwgImgiOiAiTEFQVE9QLVFVQTNOQ1AzIiwgInUiOiAiXHU1MjE4XHU5NmU4XHU4YmZhIn0="
}